btd_client/__init__.py
btd_client/source.py
btd_python-0.1.0.dist-info/METADATA
btd_python-0.1.0.dist-info/WHEEL
btd_python-0.1.0.dist-info/top_level.txt
btd_python-0.1.0.dist-info/RECORD
