Metadata-Version: 2.4
Name: btd-python
Version: 0.1.0
Summary: A python client for Baltic Transparency Data
Author-email: Sarunas Jurgilas <jurgilassarunas@yahoo.com>
License: MIT
Project-URL: Homepage, https://github.com/sarunasign/btd-python
Project-URL: Repository, https://github.com/sarunasign/btd-python
Requires-Python: >=3.7
